mcp_server_data_wrangler/__init__.py
mcp_server_data_wrangler/__main__.py
mcp_server_data_wrangler/configurations.py
mcp_server_data_wrangler/make_logger.py
mcp_server_data_wrangler/server.py
mcp_server_data_wrangler/prompts/__init__.py
mcp_server_data_wrangler/tools/__init__.py
mcp_server_data_wrangler/tools/data_count.py
mcp_server_data_wrangler/tools/data_estimated_size.py
mcp_server_data_wrangler/tools/data_max.py
mcp_server_data_wrangler/tools/data_mean.py
mcp_server_data_wrangler/tools/data_median.py
mcp_server_data_wrangler/tools/data_min.py
mcp_server_data_wrangler/tools/data_product.py
mcp_server_data_wrangler/tools/data_quantile.py
mcp_server_data_wrangler/tools/data_schema.py
mcp_server_data_wrangler/tools/data_shape.py
mcp_server_data_wrangler/tools/data_std.py
mcp_server_data_wrangler/tools/data_var.py
mcp_server_data_wrangler/tools/describe_data.py
mcp_server_data_wrangler/tools/model.py
mcp_server_data_wrangler/tools/tools.py
mcp_server_data_wrangler/utils/__init__.py
mcp_server_data_wrangler/utils/datetime_utils.py
mcp_server_data_wrangler/utils/str_utils.py
dungngo_mcp_data_wrangler-0.1.2.dist-info/METADATA
dungngo_mcp_data_wrangler-0.1.2.dist-info/WHEEL
dungngo_mcp_data_wrangler-0.1.2.dist-info/entry_points.txt
dungngo_mcp_data_wrangler-0.1.2.dist-info/licenses/LICENSE
dungngo_mcp_data_wrangler-0.1.2.dist-info/RECORD
