Metadata-Version: 2.4
Name: dungngo-mcp-data-wrangler
Version: 0.1.2
Summary: Add your description here (republished for testing)
Author-email: dungngo <test@dungngo.dev>
License-File: LICENSE
Requires-Python: >=3.11.8
Requires-Dist: aiofiles>=24.1.0
Requires-Dist: mcp[cli]>=1.6.0
Requires-Dist: numpy>=2.2.4
Requires-Dist: polars>=1.26.0
Requires-Dist: pydantic-settings>=2.8.1
Requires-Dist: pydantic>=2.11.1
Requires-Dist: python-dotenv>=1.1.0
Requires-Dist: scikit-learn>=1.6.1
